formula_fantasy/README.md
formula_fantasy/__init__.py
formula_fantasy/cli.py
formula_fantasy/core.py
formula_fantasy-1.0.4.dist-info/licenses/LICENSE
formula_fantasy-1.0.4.dist-info/METADATA
formula_fantasy-1.0.4.dist-info/WHEEL
formula_fantasy-1.0.4.dist-info/entry_points.txt
formula_fantasy-1.0.4.dist-info/top_level.txt
formula_fantasy-1.0.4.dist-info/RECORD
