Metadata-Version: 2.4
Name: formula-fantasy
Version: 1.0.4
Summary: A simple Python library for fetching F1 Fantasy driver and constructor data
Home-page: https://github.com/yourusername/formula-fantasy
Author: F1 Fantasy Data Team
Author-email: F1 Fantasy Data Team <noreply@f1fantasy.dev>
Maintainer-email: F1 Fantasy Data Team <noreply@f1fantasy.dev>
License: MIT License
Project-URL: Homepage, https://github.com/yourusername/formula-fantasy
Project-URL: Documentation, https://github.com/yourusername/formula-fantasy#readme
Project-URL: Repository, https://github.com/yourusername/formula-fantasy.git
Project-URL: Issues, https://github.com/yourusername/formula-fantasy/issues
Project-URL: Data Source, https://github.com/JoshCBruce/fantasy-data
Keywords: f1,formula1,fantasy,racing,motorsport,api,data,statistics
Classifier: Development Status :: 5 - Production/Stable
Classifier: Intended Audience :: Developers
Classifier: Intended Audience :: End Users/Desktop
Classifier: Topic :: Software Development :: Libraries :: Python Modules
Classifier: Topic :: Games/Entertainment
Classifier: Topic :: Internet :: WWW/HTTP :: Dynamic Content
Classifier: License :: OSI Approved :: MIT License
Classifier: Programming Language :: Python :: 3
Classifier: Programming Language :: Python :: 3.7
Classifier: Programming Language :: Python :: 3.8
Classifier: Programming Language :: Python :: 3.9
Classifier: Programming Language :: Python :: 3.10
Classifier: Programming Language :: Python :: 3.11
Classifier: Programming Language :: Python :: 3.12
Classifier: Operating System :: OS Independent
Requires-Python: >=3.7
License-File: LICENSE
Requires-Dist: requests>=2.25.0
Provides-Extra: dev
Requires-Dist: pytest>=6.0; extra == "dev"
Requires-Dist: pytest-cov; extra == "dev"
Requires-Dist: black; extra == "dev"
Requires-Dist: flake8; extra == "dev"
Requires-Dist: mypy; extra == "dev"
Dynamic: author
Dynamic: home-page
Dynamic: license-file
Dynamic: requires-python
